LICENSE
MANIFEST.in
README.md
setup.py
tordjango/__init__.py
tordjango.egg-info/PKG-INFO
tordjango.egg-info/SOURCES.txt
tordjango.egg-info/dependency_links.txt
tordjango.egg-info/requires.txt
tordjango.egg-info/top_level.txt
tordjango/management/__init__.py
tordjango/management/commands/__init__.py
tordjango/management/commands/runtornado.py