Metadata-Version: 1.0
Name: tordjango
Version: 0.1
Summary: Simple management command to serve Django via Tornado
Home-page: http://github.com/gulielmus/tordjango
Author: Will Barton
Author-email: willbarton@gmail.com
License: BSD
Platform: UNKNOWN
